flyhostel/__init__.py
flyhostel/__main__.py
flyhostel/_version.py
flyhostel/constants.py
flyhostel/arduino/__init__.py
flyhostel/arduino/constants.py
flyhostel/arduino/identifier.py
flyhostel/arduino/utils.py
flyhostel/data/__init__.py
flyhostel/data/behavr.py
flyhostel/data/download.py
flyhostel/data/idtrackerai.py
flyhostel/data/trajectorytools.py
flyhostel/data/upload.py
flyhostel/data/bin/__init__.py
flyhostel/data/bin/copy.py
flyhostel/data/bin/upload.py
flyhostel/ldriver/__init__.py
flyhostel/ldriver/bin/__init__.py
flyhostel/ldriver/bin/parser.py
flyhostel/ldriver/bin/run.py
flyhostel/plotting/__init__.py
flyhostel/plotting/core.py
flyhostel/plotting/environment.py
flyhostel/plotting/ethogram.py
flyhostel/plotting/sleep.py
flyhostel/plotting/synchrony.py
flyhostel/quantification/__init__.py
flyhostel/quantification/constants.py
flyhostel/quantification/data_view.py
flyhostel/quantification/ethogram.py
flyhostel/quantification/imgstore.py
flyhostel/quantification/params.py
flyhostel/quantification/sleep.py
flyhostel/quantification/utils.py
flyhostel/quantification/bin/__init__.py
flyhostel/quantification/bin/parser.py
flyhostel/quantification/bin/run.py
flyhostel/quantification/modelling/__init__.py
flyhostel/quantification/modelling/analysis.py
flyhostel/quantification/modelling/animal.py
flyhostel/quantification/modelling/behaviors.py
flyhostel/quantification/modelling/constants.py
flyhostel/quantification/modelling/manager.py
flyhostel/quantification/modelling/model.py
flyhostel/quantification/modelling/parameters.py
flyhostel/quantification/modelling/bin/__init__.py
flyhostel/quantification/modelling/bin/parser.py
flyhostel/quantification/modelling/bin/run.py
flyhostel/sensors/__init__.py
flyhostel/sensors/constants.py
flyhostel/sensors/node.py
flyhostel/sensors/sensor.py
flyhostel/sensors/server.py
flyhostel/sensors/bin/__init__.py
flyhostel/sensors/bin/parser.py
flyhostel/sensors/bin/run.py
flyhostel/sensors/io/__init__.py
flyhostel/sensors/io/io.py
flyhostel-1.1.3.dist-info/METADATA
flyhostel-1.1.3.dist-info/WHEEL
flyhostel-1.1.3.dist-info/entry_points.txt
flyhostel-1.1.3.dist-info/top_level.txt
flyhostel-1.1.3.dist-info/RECORD
